main.py
soundprompt/__init__.py
soundprompt/console.py
soundprompt/device.py
soundprompt/event.py
soundprompt/main.py
soundprompt/sound.py
soundprompt/version.py
soundprompt/worker.py
soundprompt/config/__init__.py
soundprompt/config/args.py
soundprompt/config/config.py
soundprompt/config/environment.py
soundprompt/config/toml/__init__.py
soundprompt/config/toml/config.py
soundprompt/config/toml/structure.py
soundprompt/config/toml/toml.py
soundprompt/data/__init__.py
soundprompt/data/database.py
soundprompt/data/filesystem.py
soundprompt/data/tag.py
soundprompt/retrieval/__init__.py
soundprompt/retrieval/prompter.py
soundprompt/retrieval/retrieval.py
soundprompt/utils/network.py
soundprompt/utils/version.py
soundprompt-0.1.5.dist-info/licenses/LICENSE
soundprompt-0.1.5.dist-info/METADATA
soundprompt-0.1.5.dist-info/WHEEL
soundprompt-0.1.5.dist-info/entry_points.txt
soundprompt-0.1.5.dist-info/top_level.txt
soundprompt-0.1.5.dist-info/RECORD
